[

  {"name": "concept_name", "type": "STRING"},
  {"name": "source_concept_id", "type": "INT64"},
  {"name": "source_vocabulary_id", "type": "STRING"},
  {"name": "source_domain_id", "type": "STRING"},
  {"name": "source_concept_class_id", "type": "STRING"},
  {"name": "standard_concept", "type": "STRING"},
  {"name": "concept_code", "type": "STRING"},
  {"name": "valid_start_date", "type": "STRING"},
  {"name": "valid_end_date", "type": "STRING"},
  {"name": "invalid_reason", "type": "STRING"},
  {"name": "target_concept_id", "type": "INT64"},
  {"name": "relationship_id", "type": "STRING"},
  {"name": "reverese_relationship_id", "type": "STRING"},
  {"name": "relationship_valid_start_date", "type": "STRING"},
  {"name": "relationship_end_date", "type": "STRING"},
  {"name": "invalid_reason_cr", "type": "STRING"}

]


